metarace/__init__.py
metarace/countback.py
metarace/export.py
metarace/factors.py
metarace/htlib.py
metarace/jsonconfig.py
metarace/report.py
metarace/riderdb.py
metarace/strops.py
metarace/telegraph.py
metarace/timy.py
metarace/tod.py
metarace/unt4.py
metarace/weather.py
metarace/data/IOC_Codes.csv
metarace/data/__init__.py
metarace/data/bgact-symbolic.svg
metarace/data/bgerror-symbolic.svg
metarace/data/bgidle-symbolic.svg
metarace/data/bgok-symbolic.svg
metarace/data/metarace.json
metarace/data/metarace_icon.svg
metarace/data/pdf_template.json
metarace/data/program_template.json
metarace/decoder/__init__.py
metarace/decoder/rrs.py
metarace/decoder/rru.py
metarace/decoder/thbc.py
metarace-2.1.21.dist-info/licenses/LICENSE
metarace-2.1.21.dist-info/METADATA
metarace-2.1.21.dist-info/WHEEL
metarace-2.1.21.dist-info/top_level.txt
metarace-2.1.21.dist-info/RECORD
