Metadata-Version: 2.4
Name: metarace
Version: 2.1.21
Summary: Cyclesport results and timing toolkit
Author-email: Nathan Fraser <ndf-zz@6-v.org>
License-Expression: MIT
Project-URL: homepage, https://github.com/ndf-zz/metarace
Keywords: cyclesport,results,timing
Classifier: Development Status :: 4 - Beta
Classifier: Topic :: Other/Nonlisted Topic
Classifier: Operating System :: OS Independent
Classifier: Programming Language :: Python :: 3
Requires-Python: >=3.11
License-File: LICENSE
Requires-Dist: pyserial
Requires-Dist: python-dateutil>=2.9
Requires-Dist: pycairo
Requires-Dist: PyGObject
Requires-Dist: paho-mqtt>=2.1
Requires-Dist: xlsxwriter
Requires-Dist: graphemeu
Requires-Dist: requests
Dynamic: license-file
